flaekextens/__init__.py
flaekextens/main.py
flaekextens/plugin.py
flake8_extensions-0.1.1.dist-info/METADATA
flake8_extensions-0.1.1.dist-info/WHEEL
flake8_extensions-0.1.1.dist-info/entry_points.txt
flake8_extensions-0.1.1.dist-info/top_level.txt
flake8_extensions-0.1.1.dist-info/RECORD
