Metadata-Version: 2.4
Name: flake8-extensions
Version: 0.1.1
Summary: A collection of custom flake8 extensions
Home-page: https://github.com/yourusername/flaekextens
Author: Your Name
Author-email: Your Name <your.email@example.com>
Project-URL: Homepage, https://github.com/yourusername/flake8-extensions
Classifier: Development Status :: 3 - Alpha
Classifier: Intended Audience :: Developers
Classifier: License :: OSI Approved :: MIT License
Classifier: Programming Language :: Python :: 3
Classifier: Programming Language :: Python :: 3.6
Classifier: Programming Language :: Python :: 3.7
Classifier: Programming Language :: Python :: 3.8
Classifier: Programming Language :: Python :: 3.9
Classifier: Operating System :: OS Independent
Requires-Python: >=3.7
Requires-Dist: flake8>=3.0.0
Dynamic: author
Dynamic: home-page
Dynamic: requires-python
